pulumi_lambda_builders/__init__.py
pulumi_lambda_builders/_utilities.py
pulumi_lambda_builders/build_go.py
pulumi_lambda_builders/provider.py
pulumi_lambda_builders/pulumi-plugin.json
pulumi_lambda_builders/py.typed
pulumi_lambda_builders-0.1.0.dist-info/METADATA
pulumi_lambda_builders-0.1.0.dist-info/WHEEL
pulumi_lambda_builders-0.1.0.dist-info/top_level.txt
pulumi_lambda_builders-0.1.0.dist-info/RECORD
