Metadata-Version: 2.1
Name: pulumi_lambda_builders
Version: 0.1.0
Summary: Utilities for building AWS Lambda Functions
License: Apache-2.0
Project-URL: Homepage, https://pulumi.com
Project-URL: Repository, https://github.com/pulumi/pulumi-lambda-builders
Requires-Python: >=3.8
Requires-Dist: parver >=0.2.1
Requires-Dist: pulumi <4.0.0,>=3.0.0
Requires-Dist: pulumi-aws <7.0.0,>=6.0.0
Requires-Dist: semver >=2.8.1
